<?xml version='1.0' encoding='UTF-8'?>
<items>
	<item name="lecm-dic:Бизнес роли" type="lecm-dic:dictionary">
		<items updateMode="CreateOrUpdate">
			<item name="cm:Подписанты документов" type="lecm-orgstr:business-role">
				<property name="cm:name">Подписанты документов</property>
				<property name="lecm-orgstr:business-role-identifier">LECM_SIGNERS</property><!-- Business platform Signer -->
				<property name="lecm-orgstr:business-role-is-dynamic">false</property>
				<property name="lecm-orgstr:business-role-description">Сотрудники, которые занимаются подписанием документов</property>
			</item>
			<item name="cm:Подписант документов" type="lecm-orgstr:business-role">
				<property name="cm:name">Подписант документов</property>
				<property name="lecm-orgstr:business-role-identifier">LECM_SIGNER_DYN</property>
				<property name="lecm-orgstr:business-role-is-dynamic">true</property>
				<property name="lecm-orgstr:business-role-description">Сотрудник, фактически выполнивший подписание документа</property>
			</item>
		</items>
	</item>
</items>
